{"cards":[{"id":"1","name":"Map Card","date":"2019-11-18 15:36:59","modified_date":"2019-11-19 09:32:57","favorite":"0","type":"masonry","layout":{"settings":{"type":"masonry","card_layout":"vertical","switch_layout":"768px","content_position":"bottom","media_position":"left","media_width":"50%","display_media":1,"display_overlay":0,"display_footer":1,"flex_media":0,"card_width":"500px","responsive":0},"layers":{"inner":{"media":{"media-thumbnail":{"action":[],"blocks":[]},"media-content":{"media-content-top":{"action":[],"blocks":[{"content":{"source":"media_button_block","stroke-width":"2.5","name":"wpgb-block-1","lightbox_icon":"wpgb\/arrows\/enlarge-1","play_icon":"wpgb\/multimedia\/button-play-1"},"action":[]}]},"action":[]},"action":{"action_type":"open_media"}},"content":{"body":{"action":[],"blocks":[{"content":{"source":"post_field","post_field":"the_title","idle_scheme":"scheme-1","name":"wpgb-block-2"},"action":{"link_url":"single_post","action_type":"link"}},{"content":{"source":"raw_content_block","name":"wpgb-block-3","idle_scheme":"scheme-2","raw_content":"Address, France"},"action":[]},{"content":{"source":"product_field","idle_scheme":"accent-1","hover_scheme":"accent-1","product_field":"the_price","name":"wpgb-block-4"},"action":[]}]},"footer":{"action":[],"blocks":[{"content":{"source":"svg_icon_block","name":"wpgb-block-5","svg_name":"wpgb\/home\/bed","stroke-width":2,"tag":"span"},"action":[]},{"content":{"source":"raw_content_block","name":"wpgb-block-6","raw_content":"2","tag":"span"},"action":[]},{"content":{"source":"svg_icon_block","name":"wpgb-block-7","svg_name":"wpgb\/home\/shower","stroke-width":2,"tag":"span"},"action":[]},{"content":{"source":"raw_content_block","name":"wpgb-block-8","raw_content":"1","tag":"span"},"action":[]},{"content":{"source":"raw_content_block","name":"wpgb-block-9","raw_content":"(42)","tag":"span"},"action":[]},{"content":{"source":"raw_content_block","name":"wpgb-block-10","idle_scheme":"scheme-1","raw_content":"4.50","tag":"span"},"action":[]},{"content":{"source":"svg_icon_block","name":"wpgb-block-11","svg_name":"wpgb\/user-interface\/star","stroke-width":2,"tag":"span"},"action":[]}]},"action":[]},"action":[]}},"fonts":{"google":[]}},"settings":{"general":{"type":"masonry","card_layout":"vertical","switch_layout":"768px","content_position":"bottom","media_position":"left","media_width":"50%","display_media":1,"display_overlay":0,"display_footer":1,"flex_media":0,"card_width":"500px","responsive":0,"global_css":""},"layers":{"wpgb-card-inner":{"style":{"idle":{"overflow":"hidden"},"hover":[]},"action":[],"animation":[]},"wpgb-card-media":{"animation":[],"style":{"idle":[]},"action":{"action_type":"open_media"}},"wpgb-card-media-thumbnail":{"animation":[],"style":{"idle":{"border-top-left-radius":"0.5em","border-top-right-radius":"0.5em","border-bottom-right-radius":"0.5em","border-bottom-left-radius":"0.5em"},"hover":[]},"action":[]},"wpgb-card-media-content":{"action":[],"style":{"idle":{"text-align":"right"}},"animation":[]},"wpgb-card-body":{"style":{"idle":{"padding-top":"1.125em","padding-bottom":"0.25em"}},"action":[],"animation":[]},"wpgb-card-footer":{"style":{"idle":{"padding-bottom":"0.75em","border-top-width":"1px","border-style":"solid","border-right-width":0,"border-bottom-width":0,"border-left-width":0,"border-color":"#eff3f2","padding-top":"0.75em"}},"action":[],"animation":[]}},"blocks":{"wpgb-block-1":{"content":{"source":"media_button_block","stroke-width":"2.5","name":"wpgb-block-1","lightbox_icon":"wpgb\/arrows\/enlarge-1","play_icon":"wpgb\/multimedia\/button-play-1"},"style":{"idle":{"font-size":"1em","line-height":"1em","font-weight":"700","color_scheme":"scheme-2","width":"2em","height":"2em","padding-top":"0.5em","padding-right":"0.5em","padding-bottom":"0.5em","padding-left":"0.5em","background":"#ffffff","color":"#7a7a7a","border-top-left-radius":"0.25em","border-top-right-radius":"0.25em","border-bottom-right-radius":"0.25em","border-bottom-left-radius":"0.25em","stroke-width":"2.5","display":"inline-block","margin-top":"0.5em","margin-right":"0.5em","margin-bottom":"0.5em","margin-left":"0.5em","box-shadow-blur":"0.125em","box-shadow-vertical":"0.125em","box-shadow-color":"rgba(0,0,0,0.1)","box-shadow":"0 0.125em 0.125em 0 rgba(0,0,0,0.1)"},"hover":[]},"animation":{"presets":"fade","opacity":0,"transition-duration":"200ms","transition-easing":"linear","transition-timing-function":"linear","selector":"card"},"action":[]},"wpgb-block-2":{"content":{"source":"post_field","post_field":"the_title","idle_scheme":"scheme-1","name":"wpgb-block-2"},"style":{"idle":{"font-size":"1.25em","line-height":"1.25em","font-weight":"700","color_scheme":"scheme-1","height":"1.25em","overflow":"hidden","custom_css":"text-overflow: ellipsis;\nwhite-space: nowrap;\n","width":"90%"},"hover":[]},"animation":[],"action":{"link_url":"single_post","action_type":"link"}},"wpgb-block-3":{"content":{"source":"raw_content_block","name":"wpgb-block-3","idle_scheme":"scheme-2","raw_content":"Address, France"},"style":{"idle":{"font-size":"1em","line-height":"1em","font-weight":"400","color_scheme":"scheme-2","margin-top":"0.25em"},"hover":[]},"animation":[],"action":[]},"wpgb-block-4":{"content":{"source":"product_field","idle_scheme":"accent-1","hover_scheme":"accent-1","product_field":"the_price","name":"wpgb-block-4"},"style":{"idle":{"font-size":"1.125em","line-height":"1.125em","font-weight":"600","color_scheme":"accent-1","display":"inline-block","margin-top":"1em"},"hover":{"hover_selector":"itself","color_scheme":"accent-1"}},"animation":[],"action":[]},"wpgb-block-5":{"content":{"source":"svg_icon_block","name":"wpgb-block-5","svg_name":"wpgb\/home\/bed","stroke-width":2,"tag":"span"},"style":{"idle":{"font-size":"1em","line-height":"1em","font-weight":"500","color_scheme":"scheme-1","color":"#8e8e8e","stroke-width":2,"width":"1.125em","height":"1.125em","display":"inline-block","vertical-align":"top"},"hover":[]},"animation":[],"action":[]},"wpgb-block-6":{"content":{"source":"raw_content_block","name":"wpgb-block-6","raw_content":"2","tag":"span"},"style":{"idle":{"font-size":"0.875em","line-height":"1.3em","font-weight":"500","color_scheme":"scheme-1","color":"#8e8e8e","display":"inline-block","vertical-align":"top","margin-left":"0.6em","margin-right":"0.6em"},"hover":[]},"animation":[],"action":[]},"wpgb-block-7":{"content":{"source":"svg_icon_block","name":"wpgb-block-7","svg_name":"wpgb\/home\/shower","stroke-width":2,"tag":"span"},"style":{"idle":{"font-size":"1em","line-height":"1em","font-weight":"500","color_scheme":"scheme-1","color":"#8e8e8e","stroke-width":2,"width":"1.125em","height":"1.125em","display":"inline-block","vertical-align":"top","margin-right":"0.5em","margin-left":"0.5em"},"hover":[]},"animation":[],"action":[]},"wpgb-block-8":{"content":{"source":"raw_content_block","name":"wpgb-block-8","raw_content":"1","tag":"span"},"style":{"idle":{"font-size":"0.875em","line-height":"1.3em","font-weight":"500","color_scheme":"scheme-1","color":"#8e8e8e","display":"inline-block","vertical-align":"top"},"hover":[]},"animation":[],"action":[]},"wpgb-block-9":{"content":{"source":"raw_content_block","name":"wpgb-block-9","raw_content":"(42)","tag":"span"},"style":{"idle":{"font-size":"0.875em","line-height":"1.3em","font-weight":"400","color_scheme":"scheme-1","color":"#8e8e8e","display":"inline-block","vertical-align":"top","float":"right"},"hover":[]},"animation":[],"action":[]},"wpgb-block-10":{"content":{"source":"raw_content_block","name":"wpgb-block-10","idle_scheme":"scheme-1","raw_content":"4.50","tag":"span"},"style":{"idle":{"font-size":"0.875em","line-height":"1.3em","font-weight":"500","color_scheme":"scheme-1","display":"inline-block","vertical-align":"top","float":"right","margin-right":"0.3em","margin-left":"0.3em"},"hover":[]},"animation":[],"action":[]},"wpgb-block-11":{"content":{"source":"svg_icon_block","name":"wpgb-block-11","svg_name":"wpgb\/user-interface\/star","stroke-width":2,"tag":"span"},"style":{"idle":{"font-size":"1em","line-height":"1em","font-weight":"500","color_scheme":"scheme-1","color":"#eda436","stroke-width":2,"width":"1.125em","height":"1.125em","display":"inline-block","vertical-align":"top","float":"right"},"hover":[]},"animation":[],"action":[]}}},"css":".wp-grid-builder .wpgb-card-preview .wpgb-card-body{padding-top:1.125em;padding-bottom:.25em}.wp-grid-builder .wpgb-card-preview .wpgb-card-content{-webkit-box-flex:1;-ms-flex-positive:1;flex-grow:1}.wp-grid-builder .wpgb-card-preview .wpgb-card-footer{padding-bottom:.75em;border-width:1px 0 0;border-style:solid;border-color:#eff3f2;padding-top:.75em}.wp-grid-builder .wpgb-card-preview .wpgb-card-inner{overflow:hidden}.wp-grid-builder .wpgb-card-preview .wpgb-card-media-content{text-align:right}.wp-grid-builder .wpgb-card-preview .wpgb-card-media-thumbnail{border-radius:.5em}.wp-grid-builder .wpgb-card-preview .wpgb-block-1{stroke-width:2.5;font-size:1em;line-height:1em;font-weight:700;width:2em;height:2em;padding:.5em;background:#fff;color:#7a7a7a;border-radius:.25em;display:inline-block;margin:.5em;box-shadow:rgba(0,0,0,0.1) 0 .125em .125em 0;opacity:0;-webkit-transition-timing-function:linear;transition-timing-function:linear;-webkit-transition-duration:200ms;transition-duration:200ms}.wp-grid-builder .wpgb-card-preview:hover .wpgb-block-1{opacity:1}.wp-grid-builder .wpgb-card-preview .wpgb-block-2{font-size:1.25em;line-height:1.25em;font-weight:700;height:1.25em;overflow:hidden;width:90%;text-overflow:ellipsis;white-space:nowrap}.wp-grid-builder .wpgb-card-preview .wpgb-block-3{font-size:1em;line-height:1em;font-weight:400;margin-top:.25em}.wp-grid-builder .wpgb-card-preview .wpgb-block-4{font-size:1.125em;line-height:1.125em;font-weight:600;display:inline-block;margin-top:1em}.wp-grid-builder .wpgb-card-preview .wpgb-block-5{stroke-width:2;font-size:1em;line-height:1em;font-weight:500;color:#8e8e8e;width:1.125em;height:1.125em;display:inline-block;vertical-align:top}.wp-grid-builder .wpgb-card-preview .wpgb-block-6{font-size:.875em;line-height:1.3em;font-weight:500;color:#8e8e8e;display:inline-block;vertical-align:top;margin-left:.6em;margin-right:.6em}.wp-grid-builder .wpgb-card-preview .wpgb-block-7{stroke-width:2;font-size:1em;line-height:1em;font-weight:500;color:#8e8e8e;width:1.125em;height:1.125em;display:inline-block;vertical-align:top;margin-right:.5em;margin-left:.5em}.wp-grid-builder .wpgb-card-preview .wpgb-block-8{font-size:.875em;line-height:1.3em;font-weight:500;color:#8e8e8e;display:inline-block;vertical-align:top}.wp-grid-builder .wpgb-card-preview .wpgb-block-9{font-size:.875em;line-height:1.3em;font-weight:400;color:#8e8e8e;display:inline-block;vertical-align:top;float:right}.wp-grid-builder .wpgb-card-preview .wpgb-block-10{font-size:.875em;line-height:1.3em;font-weight:500;display:inline-block;vertical-align:top;float:right;margin-right:.3em;margin-left:.3em}.wp-grid-builder .wpgb-card-preview .wpgb-block-11{stroke-width:2;font-size:1em;line-height:1em;font-weight:500;color:#eda436;width:1.125em;height:1.125em;display:inline-block;vertical-align:top;float:right}"}]}
